pkynetics/__about__.py
pkynetics/__init__.py
pkynetics/_version.py
pkynetics/py.typed
pkynetics/data/ejemplo_enfriamiento.asc
pkynetics/data/sample_dilatometry_data.asc
pkynetics/data/sample_tga_data.csv
pkynetics/data/dsc/sample_dsc_setaram.csv
pkynetics/data/dsc/sample_dsc_setaram.txt
pkynetics/data/dsc/sample_dsc_tainstruments.txt
pkynetics/data/heat_capacity/sample.txt
pkynetics/data/heat_capacity/sapphire.txt
pkynetics/data/heat_capacity/zero.txt
pkynetics/data_import/__init__.py
pkynetics/data_import/custom_importer.py
pkynetics/data_import/dilatometry_importer.py
pkynetics/data_import/dsc_importer.py
pkynetics/data_import/tga_importer.py
pkynetics/data_preprocessing/__init__.py
pkynetics/data_preprocessing/common_preprocessing.py
pkynetics/data_preprocessing/dilatometry_preprocessing.py
pkynetics/data_preprocessing/dsc_preprocessing.py
pkynetics/data_preprocessing/tga_preprocessing.py
pkynetics/model_fitting_methods/__init__.py
pkynetics/model_fitting_methods/coats_redfern.py
pkynetics/model_fitting_methods/freeman_carroll.py
pkynetics/model_fitting_methods/horowitz_metzger.py
pkynetics/model_fitting_methods/jmak.py
pkynetics/model_fitting_methods/kissinger.py
pkynetics/model_free_methods/__init__.py
pkynetics/model_free_methods/friedman_method.py
pkynetics/model_free_methods/kas_method.py
pkynetics/model_free_methods/ofw_method.py
pkynetics/result_visualization/__init__.py
pkynetics/result_visualization/dilatometry_plots.py
pkynetics/result_visualization/kinetic_plot.py
pkynetics/result_visualization/model_specific_plots.py
pkynetics/synthetic_data/__init__.py
pkynetics/synthetic_data/basic_kinetic_data.py
pkynetics/synthetic_data/model_specific_data.py
pkynetics/synthetic_data/noise_generators.py
pkynetics/technique_analysis/__init__.py
pkynetics/technique_analysis/dilatometry.py
pkynetics/technique_analysis/utilities.py
pkynetics/technique_analysis/dsc/__init__.py
pkynetics/technique_analysis/dsc/baseline.py
pkynetics/technique_analysis/dsc/core.py
pkynetics-0.4.1.dist-info/METADATA
pkynetics-0.4.1.dist-info/WHEEL
pkynetics-0.4.1.dist-info/licenses/LICENSE
pkynetics-0.4.1.dist-info/RECORD
