Metadata-Version: 2.4
Name: pkynetics
Version: 0.4.1
Summary: A comprehensive library for thermal analysis kinetic methods
Project-URL: Homepage, https://github.com/PPeitsch/pkynetics
Project-URL: Documentation, https://pkynetics.readthedocs.io/
Project-URL: Repository, https://github.com/PPeitsch/pkynetics.git
Project-URL: Bug Tracker, https://github.com/PPeitsch/pkynetics/issues
Project-URL: Changelog, https://github.com/PPeitsch/pkynetics/blob/main/CHANGELOG.md
Author-email: Pablo Peitsch <pablo.peitsch@gmail.com>
License: MIT License
License-File: LICENSE
Keywords: dilatometry,dsc,kinetics,thermal-analysis,thermogravimetry
Classifier: Development Status :: 3 - Alpha
Classifier: Environment :: Console
Classifier: Framework :: Pytest
Classifier: Intended Audience :: Science/Research
Classifier: License :: OSI Approved :: MIT License
Classifier: Natural Language :: English
Classifier: Programming Language :: Python :: 3
Classifier: Programming Language :: Python :: 3 :: Only
Classifier: Programming Language :: Python :: 3.9
Classifier: Programming Language :: Python :: 3.10
Classifier: Programming Language :: Python :: 3.11
Classifier: Topic :: Scientific/Engineering
Classifier: Topic :: Scientific/Engineering :: Chemistry
Classifier: Topic :: Scientific/Engineering :: Physics
Classifier: Typing :: Typed
Requires-Python: >=3.9
Requires-Dist: chardet>=5.0.0
Requires-Dist: matplotlib~=3.7.5
Requires-Dist: numpy~=1.24.3
Requires-Dist: pandas~=2.0.3
Requires-Dist: scikit-learn>=0.24.0
Requires-Dist: scipy~=1.10.1
Requires-Dist: seaborn>=0.11.0
Requires-Dist: statsmodels~=0.14.1
Provides-Extra: dev
Requires-Dist: black>=23.0.0; extra == 'dev'
Requires-Dist: isort>=5.0.0; extra == 'dev'
Requires-Dist: mypy>=1.0.0; extra == 'dev'
Requires-Dist: pandas-stubs>=2.0.0; extra == 'dev'
Requires-Dist: pytest-cov>=4.1.0; extra == 'dev'
Requires-Dist: pytest<8.0.0,>=6.0.0; extra == 'dev'
Requires-Dist: sphinx<6.0.0,>=4.0.0; extra == 'dev'
